tq_performance_utils/__init__.py
tq_performance_utils/profile_decorator/__init__.py
tq_performance_utils/profile_decorator/profile_decorator.py
tq_performance_utils-0.2.2.dist-info/METADATA
tq_performance_utils-0.2.2.dist-info/WHEEL
tq_performance_utils-0.2.2.dist-info/top_level.txt
tq_performance_utils-0.2.2.dist-info/RECORD
